README.md
setup.py
graff/__init__.py
graff/add.py
graff/category.py
graff/compatibility.py
graff/condition.py
graff/config.py
graff/connection.py
graff/flexible_value.py
graff/orm.py
graff/temptable.py
graff/testing.py
graff.egg-info/PKG-INFO
graff.egg-info/SOURCES.txt
graff.egg-info/dependency_links.txt
graff.egg-info/not-zip-safe
graff.egg-info/requires.txt
graff.egg-info/top_level.txt
graff/query/__init__.py
graff/query/base.py
graff/query/edge.py
graff/query/node.py