Metadata-Version: 1.2
Name: graff
Version: 1.0.1
Summary: A graph database built on top of SQLAlchemy
Home-page: https://github.com/apontzen/graff
Author: Andrew Pontzen
Author-email: a.pontzen@ucl.ac.uk
License: BSD
Platform: UNKNOWN
Classifier: Development Status :: 3 - Alpha
Classifier: Intended Audience :: Developers
Classifier: Programming Language :: Python
Classifier: Programming Language :: Python :: 2.7
Classifier: Programming Language :: Python :: 3.6
Classifier: Programming Language :: Python :: 3.7
Classifier: License :: OSI Approved :: BSD License
Requires-Python: >=2.7,!=3.0.*,!=3.1.*,!=3.2.*,!=3.3.*,!=3.4.*
